odoo/addons/ssi_task_mixin/README.rst
odoo/addons/ssi_task_mixin/__init__.py
odoo/addons/ssi_task_mixin/__manifest__.py
odoo/addons/ssi_task_mixin/i18n/ssi_task_mixin.pot
odoo/addons/ssi_task_mixin/models/__init__.py
odoo/addons/ssi_task_mixin/models/mixin_responsible_task.py
odoo/addons/ssi_task_mixin/models/mixin_task.py
odoo/addons/ssi_task_mixin/static/description/icon.png
odoo/addons/ssi_task_mixin/templates/mixin_task_templates.xml
odoo14_addon_ssi_task_mixin-14.0.2.1.0.dist-info/METADATA
odoo14_addon_ssi_task_mixin-14.0.2.1.0.dist-info/WHEEL
odoo14_addon_ssi_task_mixin-14.0.2.1.0.dist-info/top_level.txt
odoo14_addon_ssi_task_mixin-14.0.2.1.0.dist-info/RECORD
